CHANGES.txt
MANIFEST.in
README.md
setup.py
djinn_pages/__init__.py
djinn_pages/admin.py
djinn_pages/urls.py
djinn_pages.egg-info/PKG-INFO
djinn_pages.egg-info/SOURCES.txt
djinn_pages.egg-info/dependency_links.txt
djinn_pages.egg-info/entry_points.txt
djinn_pages.egg-info/not-zip-safe
djinn_pages.egg-info/requires.txt
djinn_pages.egg-info/top_level.txt
djinn_pages/migrations/0001_initial.py
djinn_pages/migrations/0002_menuitem.py
djinn_pages/migrations/0003_auto_20151112_1839.py
djinn_pages/migrations/__init__.py
djinn_pages/models/__init__.py
djinn_pages/models/menu.py
djinn_pages/templates/djinn_pages/iframe.html
djinn_pages/templates/djinn_pages/snippets/menuitem.html
djinn_pages/templatetags/__init__.py
djinn_pages/templatetags/djinn_pages_tags.py
djinn_pages/views/__init__.py
djinn_pages/views/iframe.py