Metadata-Version: 1.1
Name: djinn-pages
Version: 1.0.5
Summary: Djinn Intranet Pages
Home-page: https://github.com/PythonUnited/djinn-pages
Author: PythonUnited
Author-email: info@pythonunited.com
License: beer-ware
Keywords: Djinn Pages
Platform: UNKNOWN
Classifier: Development Status :: 5 - Production/Stable
Classifier: Framework :: Django
Classifier: Intended Audience :: Developers
Classifier: License :: Freely Distributable
Classifier: Programming Language :: Python
Classifier: Topic :: Internet :: WWW/HTTP :: Site Management
Classifier: Topic :: Software Development :: Libraries :: Application Frameworks
